{
  "version": 2,
  "name": "samsisle",
  "public": true,
  "builds": [{ "src": "next.config.js", "use": "@now/next" }],
  "routes": [
    {
      "src": "/_next/static/(?:[^/]+/pages|chunks|runtime)/.+",
      "headers": {
        "cache-control": "immutable"
      }
    },
    {
      "src": "^/service-worker.js$",
      "dest": "/_next/static/service-worker.js",
      "headers": {
        "cache-control": "public, max-age=43200, immutable",
        "Service-Worker-Allowed": "/"
      }
    },
    {
      "src": "/Recoleta-Bold.woff2",
      "headers": {
        "cache-control": "max-age=31536000"
      }
    },
    {
      "src": "/2600.svg",
      "headers": {
        "cache-control": "max-age=31536000"
      }
    },
    {
      "src": "/1f311.svg",
      "headers": {
        "cache-control": "max-age=31536000"
      }
    },
    {
      "src": "/pawel-czerwinski-_ePJEC-R0q4-unsplash.jpg",
      "headers": {
        "cache-control": "max-age=31536000"
      }
    },
    { "handle": "filesystem" },
    { "src": "/*/.*", "dest": "/_error" }
  ]
}
